environment_manager/__init__.py
environment_manager/api.py
environment_manager/utils.py
environment_manager-0.2.14.dist-info/DESCRIPTION.rst
environment_manager-0.2.14.dist-info/METADATA
environment_manager-0.2.14.dist-info/RECORD
environment_manager-0.2.14.dist-info/WHEEL
environment_manager-0.2.14.dist-info/metadata.json
environment_manager-0.2.14.dist-info/top_level.txt
environment_manager-0.2.14.dist-info/zip-safe
