Metadata-Version: 2.0
Name: environment-manager
Version: 0.2.14
Summary: A Client library for Environment Manager
Home-page: https://github.com/trainline/python-environment_manager
Author: Trainline Engineering
Author-email: platform.development@thetrainline.com
License: Apache 2.0
Keywords: environment_manager client library development
Platform: UNKNOWN
Classifier: Development Status :: 3 - Alpha
Classifier: Intended Audience :: Developers
Classifier: License :: OSI Approved :: Apache Software License
Classifier: Programming Language :: Python :: 2
Classifier: Programming Language :: Python :: 2.6
Classifier: Programming Language :: Python :: 2.7
Classifier: Programming Language :: Python :: 3
Classifier: Programming Language :: Python :: 3.3
Classifier: Programming Language :: Python :: 3.4
Classifier: Programming Language :: Python :: 3.5
Requires-Dist: requests
Requires-Dist: simplejson
